LICENSE
README.md
pyproject.toml
colorcall/__init__.py
colorcall/colorizer.py
colorcall/py.typed
colorcall.egg-info/PKG-INFO
colorcall.egg-info/SOURCES.txt
colorcall.egg-info/dependency_links.txt
colorcall.egg-info/top_level.txt