Metadata-Version: 2.4
Name: colorcall
Version: 0.3.0
Summary: Color call your caracal
Author-email: MikleSedrakyan <scriptdefender@yandex.ru>, AfanasevAndrey <scriptdefender@yandex.ru>
License: MIT License
Project-URL: Homepage, https://github.com/Sw1mmeR/colorcall/tree/main
Requires-Python: >=3.11
License-File: LICENSE
Dynamic: license-file
